{
    "wood_count": "//*[@id=\"resources-wrapper\"]/div[1]/div[2]/div[1]",
    "world_button": "//*[@id=\"wrapper\"]/div[2]/div[2]/div/div/div[1]/div[1]/div/div[1]/div[2]/div/ul/li/a",
    "world_button2": "//*[@id=\"twx-w1\"]/div/div/div/div/div/div/div/div[1]/div[1]/div/div[1]/div[2]/div",
    "login_button": "//*[@id=\"wrapper\"]/div[2]/div[1]/div[2]/div[1]/div[1]/form/button",
    "username_input": "//*[@id=\"wrapper\"]/div[2]/div[1]/div[2]/div[1]/div[1]/form/div[1]/input",
    "password_input": "//*[@id=\"wrapper\"]/div[2]/div[1]/div[2]/div[1]/div[1]/form/div[2]/input",
    "logout_button": "//*[@id=\"button-logout\"]",
    "logout_button2": "//*[@id=\"wrapper\"]/div[2]/div[1]/div[2]/div[1]/div[2]/div[2]/div/a",
    "register_button": "//*[@id=\"wrapper\"]/div[2]/div[4]/div/div[1]/div[1]/a[3]",
    "register_user_input": "/html/body/div[3]/div[3]/header/div/div[4]/div/div[1]/div[1]/form/div[1]/input",
    "register_password_input": "/html/body/div[3]/div[3]/header/div/div[4]/div/div[1]/div[1]/form/div[2]/input",
    "register_email_input": "/html/body/div[3]/div[3]/header/div/div[4]/div/div[1]/div[1]/form/div[3]/input",
    "register_accept": "//*[@id=\"accept_terms_label\"]",
    "register_submit": "/html/body/div[3]/div[3]/header/div/div[4]/div/div[1]/div[1]/button",
    "temp_email": "//*[@id=\"mail\"]",
    "temp_email2": "//*[@id=\"tm-body\"]/div[1]/div/div/div[2]/div[1]/form/div[1]/div"
}
